{
    "useLocaleNames": {
      "en-US": "إنجليزي",
      "fr-FR": "فرنسي",
      "kin-RW": "الكينيارواندية",
      "sw-TZ": "سواحيلي",
      "ar-EG": "عربي",
      "es-ES": "إسباني"
    },
    "Metadata": {
      "title": "تطبيق التعريب Next.js من فابريس",
      "description": "تطبيق التعريب Next.js من فابريس"
    },
    "Header": {
      "home": "الصفحة الرئيسية",
      "about": "حول",
      "contact": "اتصل بنا",
      "locale": "اللغة"
    },
    "Home": {
       "name": "أنا فابريس موانافونزي، أنا مهندس برمجيات"
    },
    "About": {
      "content":"أنا مهندس برمجيات ومطور ويب. أنا أحب البرمجة وأحب تطوير الويب. أنا أحب أيضًا تعلم اللغات الجديدة والتعرف على ثقافات جديدة. أنا أحب السفر والتعرف على أشخاص جدد. أنا أحب الرياضة واللياقة البدنية. أنا أحب القراءة والكتابة. أنا أحب السينما والموسيقى. أنا أحب الطهي والأكل. أنا أحب الحياة. أنا أحب الله. أنا أحب العائلة. أنا أحب الأصدقاء. أنا أحب العمل"
    },
    "Contact": {
      "content": "يمكنك الوصول إلينا على  mwanafunzifabrice@gmail.com",
      "copyright": "© 2021 فابريس موانافونزي"
    }
  }
  
  